pyscript_fsspec_client/__init__.py
pyscript_fsspec_client/_version.py
pyscript_fsspec_client/client.py
pyscript_fsspec_client/io.py
pyscript_fsspec_client-0.1.2.dist-info/METADATA
pyscript_fsspec_client-0.1.2.dist-info/WHEEL
pyscript_fsspec_client-0.1.2.dist-info/licenses/LICENSE
pyscript_fsspec_client-0.1.2.dist-info/RECORD
