Metadata-Version: 2.4
Name: pyscript-fsspec-client
Version: 0.1.2
Dynamic: Keywords
Dynamic: Project-URL
Summary: get bytes via HTTP from any backend
Author: martindurant
License: BSD 3-Clause License
License-File: LICENSE
Classifier: License :: OSI Approved :: BSD License
Classifier: Programming Language :: Python
Classifier: Programming Language :: Python :: 3
Classifier: Programming Language :: Python :: 3.9
Classifier: Programming Language :: Python :: 3.10
Classifier: Programming Language :: Python :: 3.11
Classifier: Programming Language :: Python :: 3.12
Classifier: Programming Language :: Python :: 3.13
Requires-Python: >=3.9
Requires-Dist: fsspec>=2025.3.0
Provides-Extra: test
Requires-Dist: pytest; extra == 'test'
Requires-Dist: requests; extra == 'test'
